hyphenate.py
Hyphenate-1.1.0.dist-info/DESCRIPTION.rst
Hyphenate-1.1.0.dist-info/METADATA
Hyphenate-1.1.0.dist-info/RECORD
Hyphenate-1.1.0.dist-info/WHEEL
Hyphenate-1.1.0.dist-info/metadata.json
Hyphenate-1.1.0.dist-info/top_level.txt
