Metadata-Version: 2.0
Name: Hyphenate
Version: 1.1.0
Summary: Determine hyphenation breaks in English words
Home-page: https://github.com/jfinkels/hyphenate
Author: Jeffrey Finkelstein
Author-email: jeffrey.finkelstein@gmail.com
License: Public Domain
Download-URL: https://pypi.python.org/pypi/hyphenate
Platform: any
Classifier: Development Status :: 5 - Production/Stable
Classifier: License :: Public Domain
Classifier: Natural Language :: English
Classifier: Operating System :: OS Independent
Classifier: Programming Language :: Python :: 3.5
Classifier: Topic :: Text Processing
